hyperbolic_optics/__init__.py
hyperbolic_optics/anisotropy_utils.py
hyperbolic_optics/layers.py
hyperbolic_optics/materials.py
hyperbolic_optics/mueller.py
hyperbolic_optics/plots.py
hyperbolic_optics/scenario.py
hyperbolic_optics/structure.py
hyperbolic_optics/types.py
hyperbolic_optics/waves.py
hyperbolic_optics/material_params.json
hyperbolic_optics-0.2.3.dist-info/METADATA
hyperbolic_optics-0.2.3.dist-info/WHEEL
hyperbolic_optics-0.2.3.dist-info/licenses/LICENSE
hyperbolic_optics-0.2.3.dist-info/RECORD
