Metadata-Version: 2.4
Name: hyperbolic-optics
Version: 0.2.3
Summary: 4x4 Transfer Matrix Method for Anisotropic Multilayer Structures, with Mueller Matrix Calculations
Project-URL: Homepage, https://github.com/MarkCunningham0410/hyperbolic_optics
Project-URL: Repository, https://github.com/MarkCunningham0410/hyperbolic_optics
Project-URL: Issues, https://github.com/MarkCunningham0410/hyperbolic_optics/issues
Project-URL: Documentation, https://github.com/MarkCunningham0410/hyperbolic_optics
Author-email: Mark Cunningham <m.cunningham.2@research.gla.ac.uk>
License: MIT License
License-File: LICENSE
Keywords: anisotropic,hyperbolic,mueller matrix,optics,physics,simulation
Classifier: Development Status :: 3 - Alpha
Classifier: Intended Audience :: Science/Research
Classifier: License :: OSI Approved :: MIT License
Classifier: Operating System :: OS Independent
Classifier: Programming Language :: Python :: 3
Classifier: Programming Language :: Python :: 3.12
Classifier: Programming Language :: Python :: 3.13
Classifier: Topic :: Scientific/Engineering :: Physics
Requires-Python: >=3.12
Requires-Dist: matplotlib>=3.5.0
Requires-Dist: numpy>=1.20.0
Requires-Dist: scipy>=1.7.0
Provides-Extra: dev
Requires-Dist: black; extra == 'dev'
Requires-Dist: flake8; extra == 'dev'
Requires-Dist: isort; extra == 'dev'
Requires-Dist: pytest-cov; extra == 'dev'
Requires-Dist: pytest>=7.0; extra == 'dev'
Provides-Extra: docs
Requires-Dist: mdx-truly-sane-lists>=1.3; extra == 'docs'
Requires-Dist: mkdocs-jupyter>=0.24.0; extra == 'docs'
Requires-Dist: mkdocs-material>=9.5.0; extra == 'docs'
Requires-Dist: mkdocstrings[python]>=0.24.0; extra == 'docs'
